{"cameraMode":{"drawMode":0,"name":"Shaded","section":"Shading Mode"},"sceneLighting":true,"audioPlay":false,"sceneViewState":{"m_AlwaysRefresh":false,"showFog":true,"showSkybox":true,"showFlares":true,"showImageEffects":true,"showParticleSystems":true,"showVisualEffectGraphs":true,"m_FxEnabled":true},"in2DMode":false,"pivot":{"x":-9.439208030700684,"y":-2.2405951023101808,"z":6.996363639831543},"rotation":{"x":0.19993925094604493,"y":-0.004469410050660372,"z":0.0006269924924708903,"w":0.9797099828720093},"size":10.0,"orthographic":false}